setup.py
clt_wenlin/__init__.py
clt_wenlin.egg-info/PKG-INFO
clt_wenlin.egg-info/SOURCES.txt
clt_wenlin.egg-info/dependency_links.txt
clt_wenlin.egg-info/top_level.txt