Metadata-Version: 1.1
Name: clt-wenlin
Version: 0.5
Summary: Helper module for Cloud Language Tools, download wenlin data
Home-page: https://github.com/Language-Tools/cloud-language-tools-core
Author: Luc
Author-email: languagetools@mailc.net
License: GPL
Platform: UNKNOWN
Classifier: Programming Language :: Python :: 3.7
Classifier: Programming Language :: Python :: 3.8
Classifier: Topic :: Text Processing :: Linguistic
